{"filter":false,"title":"mock-product.json","tooltip":"/public_html/assets/js/mock-product.json","undoManager":{"mark":0,"position":0,"stack":[[{"start":{"row":0,"column":0},"end":{"row":17,"column":1},"action":"insert","lines":["{","    \"categories\": {","        \"Ring\": 1","    },","    \"tags\": {","        \"gold\": 1,","        \"silver\": 1","    },","    \"products\": [{","        \"product_id\": \"1\",","        \"name\": \"Sample Ring\",","        \"description\": \"This is a sample ring\",","        \"price\": \"100.00\",","        \"category\": \"Ring\",","        \"tags\": [\"gold\", \"silver\"],","        \"img\": [\"img1.jpg\"]","    }]","}"],"id":1}]]},"ace":{"folds":[],"scrolltop":0,"scrollleft":0,"selection":{"start":{"row":17,"column":1},"end":{"row":17,"column":1},"isBackwards":false},"options":{"guessTabSize":true,"useWrapMode":false,"wrapToView":true},"firstLineState":0},"timestamp":1454183974948,"hash":"c2448564315ec1ed3095f1160e15b236d845517b"}